Workbook
Name Cat: '[1]SITE SHEET'!$V$4:$V$13
Name Cat: '[2]SITE SHEET'!$V$4:$V$13
Name Category: [1]States!$H$5:$H$13
Name Category: [2]States!$H$5:$H$13
Name CostShare: [1]States!$K$4:$K$8
Name CostShare: [2]States!$K$4:$K$8
Name Disaster_Type: [1]States!$J$5:$J$6
Name Disaster_Type: [2]States!$J$5:$J$6
Name FEMACC: FEMAcostcodes!$A$4:$A$968
Name FEMACC: [2]CODES!#REF!
Name FEMACCD: FEMAcostcodes!$I$4:$I$968
Name FEMACCD: [2]CODES!#REF!
Name FEMACCR: FEMAcostcodes!$D$4:$D$968
Name FEMACCR: [2]CODES!#REF!
Name FEMACCU: FEMAcostcodes!$C$4:$C$968
Name FEMACCU: [2]CODES!#REF!
Name femacode: FEMAcostcodes!$I$620:$I$961
Name femacode: [2]CODES!#REF!
Name FEMAEC: FEMAcostcodes!$F$620:$F$961
Name FEMAEC: [2]CODES!#REF!
Name FEMAECODE: FEMAcostcodes!$A$620:$A$962
Name FEMAECODE: [2]CODES!#REF!
Name FEMAEHP: FEMAcostcodes!$F$620:$F$961
Name FEMAEHP: [2]CODES!#REF!
Name FEMAEN: FEMAcostcodes!$E$620:$E$961
Name FEMAEN: [2]CODES!#REF!
Name FEMAER: FEMAcostcodes!$D$620:$D$961
Name FEMAER: [2]CODES!#REF!
Name FEMAES: FEMAcostcodes!$D$620:$D$961
Name FEMAES: [2]CODES!#REF!
Name OPERATOR: OFFSET('[1]PAYROLL DATA'!$B$10,0,0,COUNTA('[1]PAYROLL DATA'!$B:$B),1)
Name OPERATOR: OFFSET('[2]PAYROLL DATA'!$B$10,0,0,COUNTA('[2]PAYROLL DATA'!$B:$B),1)
Name OTTYPE: '[3]PAYROLL DATA'!#REF!
Name OTTYPE: '[4]PAYROLL DATA'!#REF!
Name PAYROLLDATA: OFFSET('[1]PAYROLL DATA'!$B$9,0,0,COUNTA('[1]PAYROLL DATA'!$B:$B),1)
Name PAYROLLDATA: OFFSET('[2]PAYROLL DATA'!$B$9,0,0,COUNTA('[2]PAYROLL DATA'!$B:$B),1)
Name ProjectType: [1]Utility!$AW$8:$AW$10
Name ProjectType: [2]Utility!$AW$8:$AW$10
Name States: [1]States!$A$1:$A$52
Name States: [2]States!$A$1:$A$52
Name Yes_No: [1]States!$I$5:$I$6
Name Yes_No: [2]States!$I$5:$I$6

Sheet Estimate
F1: Category Summary
F2: A | G2: =SUMIF($A$11:$A$84,F2,$G$11:$G$84) -> 0
F3: B | G3: =SUMIF($A$11:$A$84,F3,$G$11:$G$84) -> 0
F4: C | G4: =SUMIF($A$11:$A$84,F4,$G$11:$G$84) -> 0
F5: D | G5: =SUMIF($A$11:$A$84,F5,$G$11:$G$84) -> 0
F6: E | G6: =SUMIF($A$11:$A$84,F6,$G$11:$G$84) -> 0
F7: TOTAL | G7: =SUM(G2:G6) -> 0
A10: Category | B10: Cost Code | C10: Description | D10: Unit Cost | E10: Unit | F10: Quantity | G10: Sub Total | H10: Comments | LZ10: Cost Code | MA10: Unit | MB10: Description | MC10: Unit Cost | MD10: Comments
C11: =IF(ISBLANK(B11)," ",VLOOKUP(B11,LZ11:MD1235,3,FALSE)) | D11: =IF(ISBLANK(B11)," ",VLOOKUP(B11,LZ11:MD1235,4,FALSE)) | E11: =IF(ISBLANK(B11)," ",VLOOKUP(B11,LZ11:MD1235,2,FALSE)) | G11: =IF(ISERROR(D11*F11)," ",D11*F11) | LZ11: 0 | MA11: LS | MB11: ****************************************** create line | MC11: $ 0.00
C12: =IF(ISBLANK(B12)," ",VLOOKUP(B12,LZ12:MD1236,3,FALSE)) | D12: =IF(ISBLANK(B12)," ",VLOOKUP(B12,LZ12:MD1236,4,FALSE)) | E12: =IF(ISBLANK(B12)," ",VLOOKUP(B12,LZ12:MD1236,2,FALSE)) | G12: =IF(ISERROR(D12*F12)," ",D12*F12) | LZ12: 852 | MA12: LS | MB12: STATE MANAGEMENT COSTS | MC12: $ 0.00
C13: =IF(ISBLANK(B13)," ",VLOOKUP(B13,LZ13:MD1237,3,FALSE)) | D13: =IF(ISBLANK(B13)," ",VLOOKUP(B13,LZ13:MD1237,4,FALSE)) | E13: =IF(ISBLANK(B13)," ",VLOOKUP(B13,LZ13:MD1237,2,FALSE)) | G13: =IF(ISERROR(D13*F13)," ",D13*F13) | MB13: State Management Costs
C14: =IF(ISBLANK(B14)," ",VLOOKUP(B14,LZ14:MD1238,3,FALSE)) | D14: =IF(ISBLANK(B14)," ",VLOOKUP(B14,LZ14:MD1238,4,FALSE)) | E14: =IF(ISBLANK(B14)," ",VLOOKUP(B14,LZ14:MD1238,2,FALSE)) | G14: =IF(ISERROR(D14*F14)," ",D14*F14) | LZ14: 909 | MA14: LS | MB14: MITIGATION | MC14: $ 0.00
C15: =IF(ISBLANK(B15)," ",VLOOKUP(B15,LZ15:MD1239,3,FALSE)) | D15: =IF(ISBLANK(B15)," ",VLOOKUP(B15,LZ15:MD1239,4,FALSE)) | E15: =IF(ISBLANK(B15)," ",VLOOKUP(B15,LZ15:MD1239,2,FALSE)) | G15: =IF(ISERROR(D15*F15)," ",D15*F15) | MB15: Mitigation
C16: =IF(ISBLANK(B16)," ",VLOOKUP(B16,LZ16:MD1240,3,FALSE)) | D16: =IF(ISBLANK(B16)," ",VLOOKUP(B16,LZ16:MD1240,4,FALSE)) | E16: =IF(ISBLANK(B16)," ",VLOOKUP(B16,LZ16:MD1240,2,FALSE)) | G16: =IF(ISERROR(D16*F16)," ",D16*F16) | LZ16: 1001 | MA16: TON | MB16: DEBRIS (SEDIMENTS, CONCENTRATED) | MC16: $ 0.00
C17: =IF(ISBLANK(B17)," ",VLOOKUP(B17,LZ17:MD1241,3,FALSE)) | D17: =IF(ISBLANK(B17)," ",VLOOKUP(B17,LZ17:MD1241,4,FALSE)) | E17: =IF(ISBLANK(B17)," ",VLOOKUP(B17,LZ17:MD1241,2,FALSE)) | G17: =IF(ISERROR(D17*F17)," ",D17*F17) | MB17: Debris, sediments, concentrated
C18: =IF(ISBLANK(B18)," ",VLOOKUP(B18,LZ18:MD1242,3,FALSE)) | D18: =IF(ISBLANK(B18)," ",VLOOKUP(B18,LZ18:MD1242,4,FALSE)) | E18: =IF(ISBLANK(B18)," ",VLOOKUP(B18,LZ18:MD1242,2,FALSE)) | G18: =IF(ISERROR(D18*F18)," ",D18*F18) | LZ18: 1002 | MA18: TON | MB18: DEBRIS, (SEDIMENTS, SCATTERED) | MC18: $ 0.00
C19: =IF(ISBLANK(B19)," ",VLOOKUP(B19,LZ19:MD1243,3,FALSE)) | D19: =IF(ISBLANK(B19)," ",VLOOKUP(B19,LZ19:MD1243,4,FALSE)) | E19: =IF(ISBLANK(B19)," ",VLOOKUP(B19,LZ19:MD1243,2,FALSE)) | G19: =IF(ISERROR(D19*F19)," ",D19*F19) | MB19: Debris, (sedimetns, scattered)
C20: =IF(ISBLANK(B20)," ",VLOOKUP(B20,LZ20:MD1244,3,FALSE)) | D20: =IF(ISBLANK(B20)," ",VLOOKUP(B20,LZ20:MD1244,4,FALSE)) | E20: =IF(ISBLANK(B20)," ",VLOOKUP(B20,LZ20:MD1244,2,FALSE)) | G20: =IF(ISERROR(D20*F20)," ",D20*F20) | LZ20: 1003 | MA20: TON | MB20: DEBRIS (PERSONAL PROPERTY CURB) | MC20: $ 0.00
C21: =IF(ISBLANK(B21)," ",VLOOKUP(B21,LZ21:MD1245,3,FALSE)) | D21: =IF(ISBLANK(B21)," ",VLOOKUP(B21,LZ21:MD1245,4,FALSE)) | E21: =IF(ISBLANK(B21)," ",VLOOKUP(B21,LZ21:MD1245,2,FALSE)) | G21: =IF(ISERROR(D21*F21)," ",D21*F21) | MB21: Should not be limited to private residences. Labor and equipment required
C22: =IF(ISBLANK(B22)," ",VLOOKUP(B22,LZ22:MD1246,3,FALSE)) | D22: =IF(ISBLANK(B22)," ",VLOOKUP(B22,LZ22:MD1246,4,FALSE)) | E22: =IF(ISBLANK(B22)," ",VLOOKUP(B22,LZ22:MD1246,2,FALSE)) | G22: =IF(ISERROR(D22*F22)," ",D22*F22) | MB22: to remove damaged personal property. Property such as furniture or appliances, from curb side of private residences. Does not include dump
C23: =IF(ISBLANK(B23)," ",VLOOKUP(B23,LZ23:MD1247,3,FALSE)) | D23: =IF(ISBLANK(B23)," ",VLOOKUP(B23,LZ23:MD1247,4,FALSE)) | E23: =IF(ISBLANK(B23)," ",VLOOKUP(B23,LZ23:MD1247,2,FALSE)) | G23: =IF(ISERROR(D23*F23)," ",D23*F23) | MB23: charges.
C24: =IF(ISBLANK(B24)," ",VLOOKUP(B24,LZ24:MD1248,3,FALSE)) | D24: =IF(ISBLANK(B24)," ",VLOOKUP(B24,LZ24:MD1248,4,FALSE)) | E24: =IF(ISBLANK(B24)," ",VLOOKUP(B24,LZ24:MD1248,2,FALSE)) | G24: =IF(ISERROR(D24*F24)," ",D24*F24) | LZ24: 1004 | MA24: TON | MB24: DEBRIS (TREES & LIMBS, CONCENTRATED) | MC24: $ 0.00
C25: =IF(ISBLANK(B25)," ",VLOOKUP(B25,LZ25:MD1249,3,FALSE)) | D25: =IF(ISBLANK(B25)," ",VLOOKUP(B25,LZ25:MD1249,4,FALSE)) | E25: =IF(ISBLANK(B25)," ",VLOOKUP(B25,LZ25:MD1249,2,FALSE)) | G25: =IF(ISERROR(D25*F25)," ",D25*F25) | MB25: Broken trees and limbs that have been picked up and brought to an
C26: =IF(ISBLANK(B26)," ",VLOOKUP(B26,LZ26:MD1250,3,FALSE)) | D26: =IF(ISBLANK(B26)," ",VLOOKUP(B26,LZ26:MD1250,4,FALSE)) | E26: =IF(ISBLANK(B26)," ",VLOOKUP(B26,LZ26:MD1250,2,FALSE)) | G26: =IF(ISERROR(D26*F26)," ",D26*F26) | MB26: assembly area. May also include localized heavy tree damage in a park or
C27: =IF(ISBLANK(B27)," ",VLOOKUP(B27,LZ27:MD1251,3,FALSE)) | D27: =IF(ISBLANK(B27)," ",VLOOKUP(B27,LZ27:MD1251,4,FALSE)) | E27: =IF(ISBLANK(B27)," ",VLOOKUP(B27,LZ27:MD1251,2,FALSE)) | G27: =IF(ISERROR(D27*F27)," ",D27*F27) | MB27: other location,
C28: =IF(ISBLANK(B28)," ",VLOOKUP(B28,LZ28:MD1252,3,FALSE)) | D28: =IF(ISBLANK(B28)," ",VLOOKUP(B28,LZ28:MD1252,4,FALSE)) | E28: =IF(ISBLANK(B28)," ",VLOOKUP(B28,LZ28:MD1252,2,FALSE)) | G28: =IF(ISERROR(D28*F28)," ",D28*F28) | LZ28: 1005 | MA28: TON | MB28: DEBRIS (TREES & LIMBS, SCATTERED) | MC28: $ 0.00
C29: =IF(ISBLANK(B29)," ",VLOOKUP(B29,LZ29:MD1253,3,FALSE)) | D29: =IF(ISBLANK(B29)," ",VLOOKUP(B29,LZ29:MD1253,4,FALSE)) | E29: =IF(ISBLANK(B29)," ",VLOOKUP(B29,LZ29:MD1253,2,FALSE)) | G29: =IF(ISERROR(D29*F29)," ",D29*F29) | MB29: Debris, (trees & limbs, scattered)
C30: =IF(ISBLANK(B30)," ",VLOOKUP(B30,LZ30:MD1254,3,FALSE)) | D30: =IF(ISBLANK(B30)," ",VLOOKUP(B30,LZ30:MD1254,4,FALSE)) | E30: =IF(ISBLANK(B30)," ",VLOOKUP(B30,LZ30:MD1254,2,FALSE)) | G30: =IF(ISERROR(D30*F30)," ",D30*F30) | LZ30: 1010 | MA30: CY | MB30: DEBRIS, (SEDIMENTS, CONCENTRATED) | MC30: $ 3.00
C31: =IF(ISBLANK(B31)," ",VLOOKUP(B31,LZ31:MD1255,3,FALSE)) | D31: =IF(ISBLANK(B31)," ",VLOOKUP(B31,LZ31:MD1255,4,FALSE)) | E31: =IF(ISBLANK(B31)," ",VLOOKUP(B31,LZ31:MD1255,2,FALSE)) | G31: =IF(ISERROR(D31*F31)," ",D31*F31) | MB31: Removal of concentrated sediment
C32: =IF(ISBLANK(B32)," ",VLOOKUP(B32,LZ32:MD1256,3,FALSE)) | D32: =IF(ISBLANK(B32)," ",VLOOKUP(B32,LZ32:MD1256,4,FALSE)) | E32: =IF(ISBLANK(B32)," ",VLOOKUP(B32,LZ32:MD1256,2,FALSE)) | G32: =IF(ISERROR(D32*F32)," ",D32*F32) | LZ32: 1011 | MA32: CY | MB32: DEBRIS, (SEDIMENTS, SCATTERED) | MC32: $ 4.00
C33: =IF(ISBLANK(B33)," ",VLOOKUP(B33,LZ33:MD1257,3,FALSE)) | D33: =IF(ISBLANK(B33)," ",VLOOKUP(B33,LZ33:MD1257,4,FALSE)) | E33: =IF(ISBLANK(B33)," ",VLOOKUP(B33,LZ33:MD1257,2,FALSE)) | G33: =IF(ISERROR(D33*F33)," ",D33*F33) | MB33: Removal of scattered sediments
C34: =IF(ISBLANK(B34)," ",VLOOKUP(B34,LZ34:MD1258,3,FALSE)) | D34: =IF(ISBLANK(B34)," ",VLOOKUP(B34,LZ34:MD1258,4,FALSE)) | E34: =IF(ISBLANK(B34)," ",VLOOKUP(B34,LZ34:MD1258,2,FALSE)) | G34: =IF(ISERROR(D34*F34)," ",D34*F34) | LZ34: 1012 | MA34: CY | MB34: DEBRIS (PERSONAL PROPERTY CURB) | MC34: $ 3.50
C35: =IF(ISBLANK(B35)," ",VLOOKUP(B35,LZ35:MD1259,3,FALSE)) | D35: =IF(ISBLANK(B35)," ",VLOOKUP(B35,LZ35:MD1259,4,FALSE)) | E35: =IF(ISBLANK(B35)," ",VLOOKUP(B35,LZ35:MD1259,2,FALSE)) | G35: =IF(ISERROR(D35*F35)," ",D35*F35) | MB35: Should not be limited to private residences. Labor and equipment required
C36: =IF(ISBLANK(B36)," ",VLOOKUP(B36,LZ36:MD1260,3,FALSE)) | D36: =IF(ISBLANK(B36)," ",VLOOKUP(B36,LZ36:MD1260,4,FALSE)) | E36: =IF(ISBLANK(B36)," ",VLOOKUP(B36,LZ36:MD1260,2,FALSE)) | G36: =IF(ISERROR(D36*F36)," ",D36*F36) | MB36: to remove damaged personal property, such as furniture or appliances,
C37: =IF(ISBLANK(B37)," ",VLOOKUP(B37,LZ37:MD1261,3,FALSE)) | D37: =IF(ISBLANK(B37)," ",VLOOKUP(B37,LZ37:MD1261,4,FALSE)) | E37: =IF(ISBLANK(B37)," ",VLOOKUP(B37,LZ37:MD1261,2,FALSE)) | G37: =IF(ISERROR(D37*F37)," ",D37*F37) | MB37: from curb side of private residences. Does not include dump charges.
C38: =IF(ISBLANK(B38)," ",VLOOKUP(B38,LZ38:MD1262,3,FALSE)) | D38: =IF(ISBLANK(B38)," ",VLOOKUP(B38,LZ38:MD1262,4,FALSE)) | E38: =IF(ISBLANK(B38)," ",VLOOKUP(B38,LZ38:MD1262,2,FALSE)) | G38: =IF(ISERROR(D38*F38)," ",D38*F38) | MB38: assembly area. May also include localized heavy tree damage in a park or
C39: =IF(ISBLANK(B39)," ",VLOOKUP(B39,LZ39:MD1263,3,FALSE)) | D39: =IF(ISBLANK(B39)," ",VLOOKUP(B39,LZ39:MD1263,4,FALSE)) | E39: =IF(ISBLANK(B39)," ",VLOOKUP(B39,LZ39:MD1263,2,FALSE)) | G39: =IF(ISERROR(D39*F39)," ",D39*F39) | MB39: other location,
C40: =IF(ISBLANK(B40)," ",VLOOKUP(B40,LZ40:MD1264,3,FALSE)) | D40: =IF(ISBLANK(B40)," ",VLOOKUP(B40,LZ40:MD1264,4,FALSE)) | E40: =IF(ISBLANK(B40)," ",VLOOKUP(B40,LZ40:MD1264,2,FALSE)) | G40: =IF(ISERROR(D40*F40)," ",D40*F40) | LZ40: 1005 | MA40: TON | MB40: DEBRIS (TREES & LIMBS, SCATTERED) | MC40: $ 0.00
C41: =IF(ISBLANK(B41)," ",VLOOKUP(B41,LZ41:MD1265,3,FALSE)) | D41: =IF(ISBLANK(B41)," ",VLOOKUP(B41,LZ41:MD1265,4,FALSE)) | E41: =IF(ISBLANK(B41)," ",VLOOKUP(B41,LZ41:MD1265,2,FALSE)) | G41: =IF(ISERROR(D41*F41)," ",D41*F41) | MB41: Debris, (trees & limbs, scattered)
C42: =IF(ISBLANK(B42)," ",VLOOKUP(B42,LZ42:MD1266,3,FALSE)) | D42: =IF(ISBLANK(B42)," ",VLOOKUP(B42,LZ42:MD1266,4,FALSE)) | E42: =IF(ISBLANK(B42)," ",VLOOKUP(B42,LZ42:MD1266,2,FALSE)) | G42: =IF(ISERROR(D42*F42)," ",D42*F42) | LZ42: 1010 | MA42: CY | MB42: DEBRIS, (SEDIMENTS, CONCENTRATED) | MC42: $ 3.00
C43: =IF(ISBLANK(B43)," ",VLOOKUP(B43,LZ43:MD1267,3,FALSE)) | D43: =IF(ISBLANK(B43)," ",VLOOKUP(B43,LZ43:MD1267,4,FALSE)) | E43: =IF(ISBLANK(B43)," ",VLOOKUP(B43,LZ43:MD1267,2,FALSE)) | G43: =IF(ISERROR(D43*F43)," ",D43*F43) | MB43: Removal of concentrated sediment
C44: =IF(ISBLANK(B44)," ",VLOOKUP(B44,LZ44:MD1268,3,FALSE)) | D44: =IF(ISBLANK(B44)," ",VLOOKUP(B44,LZ44:MD1268,4,FALSE)) | E44: =IF(ISBLANK(B44)," ",VLOOKUP(B44,LZ44:MD1268,2,FALSE)) | G44: =IF(ISERROR(D44*F44)," ",D44*F44) | LZ44: 1011 | MA44: CY | MB44: DEBRIS, (SEDIMENTS, SCATTERED) | MC44: $ 4.00
C45: =IF(ISBLANK(B45)," ",VLOOKUP(B45,LZ45:MD1269,3,FALSE)) | D45: =IF(ISBLANK(B45)," ",VLOOKUP(B45,LZ45:MD1269,4,FALSE)) | E45: =IF(ISBLANK(B45)," ",VLOOKUP(B45,LZ45:MD1269,2,FALSE)) | G45: =IF(ISERROR(D45*F45)," ",D45*F45) | MB45: Removal of scattered sediments
C46: =IF(ISBLANK(B46)," ",VLOOKUP(B46,LZ46:MD1270,3,FALSE)) | D46: =IF(ISBLANK(B46)," ",VLOOKUP(B46,LZ46:MD1270,4,FALSE)) | E46: =IF(ISBLANK(B46)," ",VLOOKUP(B46,LZ46:MD1270,2,FALSE)) | G46: =IF(ISERROR(D46*F46)," ",D46*F46) | LZ46: 1012 | MA46: CY | MB46: DEBRIS (PERSONAL PROPERTY CURB) | MC46: $ 3.50
C47: =IF(ISBLANK(B47)," ",VLOOKUP(B47,LZ47:MD1271,3,FALSE)) | D47: =IF(ISBLANK(B47)," ",VLOOKUP(B47,LZ47:MD1271,4,FALSE)) | E47: =IF(ISBLANK(B47)," ",VLOOKUP(B47,LZ47:MD1271,2,FALSE)) | G47: =IF(ISERROR(D47*F47)," ",D47*F47) | MB47: Should not be limited to private residences. Labor and equipment required
C48: =IF(ISBLANK(B48)," ",VLOOKUP(B48,LZ48:MD1272,3,FALSE)) | D48: =IF(ISBLANK(B48)," ",VLOOKUP(B48,LZ48:MD1272,4,FALSE)) | E48: =IF(ISBLANK(B48)," ",VLOOKUP(B48,LZ48:MD1272,2,FALSE)) | G48: =IF(ISERROR(D48*F48)," ",D48*F48) | MB48: to remove damaged personal property, such as furniture or appliances,
C49: =IF(ISBLANK(B49)," ",VLOOKUP(B49,LZ49:MD1273,3,FALSE)) | D49: =IF(ISBLANK(B49)," ",VLOOKUP(B49,LZ49:MD1273,4,FALSE)) | E49: =IF(ISBLANK(B49)," ",VLOOKUP(B49,LZ49:MD1273,2,FALSE)) | G49: =IF(ISERROR(D49*F49)," ",D49*F49) | MB49: from curb side of private residences. Does not include dump charges.
C50: =IF(ISBLANK(B50)," ",VLOOKUP(B50,LZ50:MD1262,3,FALSE)) | D50: =IF(ISBLANK(B50)," ",VLOOKUP(B50,LZ50:MD1262,4,FALSE)) | E50: =IF(ISBLANK(B50)," ",VLOOKUP(B50,LZ50:MD1262,2,FALSE)) | G50: =IF(ISERROR(D50*F50)," ",D50*F50) | LZ50: 1015 | MA50: CY | MB50: DEBRIS (TREES & LIMBS, SCATTERED | MC50: $ 6.00
C51: =IF(ISBLANK(B51)," ",VLOOKUP(B51,LZ51:MD1263,3,FALSE)) | D51: =IF(ISBLANK(B51)," ",VLOOKUP(B51,LZ51:MD1263,4,FALSE)) | E51: =IF(ISBLANK(B51)," ",VLOOKUP(B51,LZ51:MD1263,2,FALSE)) | G51: =IF(ISERROR(D51*F51)," ",D51*F51) | MB51: Broken trees and limbs scattered around affected area.
C52: =IF(ISBLANK(B52)," ",VLOOKUP(B52,LZ52:MD1264,3,FALSE)) | D52: =IF(ISBLANK(B52)," ",VLOOKUP(B52,LZ52:MD1264,4,FALSE)) | E52: =IF(ISBLANK(B52)," ",VLOOKUP(B52,LZ52:MD1264,2,FALSE)) | G52: =IF(ISERROR(D52*F52)," ",D52*F52) | LZ52: 1016 | MA52: MI | MB52: DEBRIS (W INDBLOW N TREES ALONG ROW -MAXIMUM DENSITY) | MC52: $ 5,000.00
C53: =IF(ISBLANK(B53)," ",VLOOKUP(B53,LZ53:MD1265,3,FALSE)) | D53: =IF(ISBLANK(B53)," ",VLOOKUP(B53,LZ53:MD1265,4,FALSE)) | E53: =IF(ISBLANK(B53)," ",VLOOKUP(B53,LZ53:MD1265,2,FALSE)) | G53: =IF(ISERROR(D53*F53)," ",D53*F53) | MB53: In a major disaster there may be extensive debris from trees and limbs
C54: =IF(ISBLANK(B54)," ",VLOOKUP(B54,LZ54:MD1266,3,FALSE)) | D54: =IF(ISBLANK(B54)," ",VLOOKUP(B54,LZ54:MD1266,4,FALSE)) | E54: =IF(ISBLANK(B54)," ",VLOOKUP(B54,LZ54:MD1266,2,FALSE)) | G54: =IF(ISERROR(D54*F54)," ",D54*F54) | MB54: over several miles of roads or streets.
C55: =IF(ISBLANK(B55)," ",VLOOKUP(B55,LZ55:MD1267,3,FALSE)) | D55: =IF(ISBLANK(B55)," ",VLOOKUP(B55,LZ55:MD1267,4,FALSE)) | E55: =IF(ISBLANK(B55)," ",VLOOKUP(B55,LZ55:MD1267,2,FALSE)) | G55: =IF(ISERROR(D55*F55)," ",D55*F55) | LZ55: 1017 | MA55: CY | MB55: DEBRIS LOADED AND HAULED TO TDRS | MC55: $ 11.25
C56: =IF(ISBLANK(B56)," ",VLOOKUP(B56,LZ56:MD1268,3,FALSE)) | D56: =IF(ISBLANK(B56)," ",VLOOKUP(B56,LZ56:MD1268,4,FALSE)) | E56: =IF(ISBLANK(B56)," ",VLOOKUP(B56,LZ56:MD1268,2,FALSE)) | G56: =IF(ISERROR(D56*F56)," ",D56*F56) | MB56: Debris loaded and hauled to TDRS (Temporary Debris Reduction Site)
C57: =IF(ISBLANK(B57)," ",VLOOKUP(B57,LZ57:MD1269,3,FALSE)) | D57: =IF(ISBLANK(B57)," ",VLOOKUP(B57,LZ57:MD1269,4,FALSE)) | E57: =IF(ISBLANK(B57)," ",VLOOKUP(B57,LZ57:MD1269,2,FALSE)) | G57: =IF(ISERROR(D57*F57)," ",D57*F57) | LZ57: 1020 | MA57: CY | MB57: DEBRIS (W ATERWAY STRUCTURE) | MC57: $ 8.00
C58: =IF(ISBLANK(B58)," ",VLOOKUP(B58,LZ58:MD1270,3,FALSE)) | D58: =IF(ISBLANK(B58)," ",VLOOKUP(B58,LZ58:MD1270,4,FALSE)) | E58: =IF(ISBLANK(B58)," ",VLOOKUP(B58,LZ58:MD1270,2,FALSE)) | G58: =IF(ISERROR(D58*F58)," ",D58*F58) | MB58: Debris that has been deposited by floodwater on levees, dams,settling
C59: =IF(ISBLANK(B59)," ",VLOOKUP(B59,LZ59:MD1271,3,FALSE)) | D59: =IF(ISBLANK(B59)," ",VLOOKUP(B59,LZ59:MD1271,4,FALSE)) | E59: =IF(ISBLANK(B59)," ",VLOOKUP(B59,LZ59:MD1271,2,FALSE)) | G59: =IF(ISERROR(D59*F59)," ",D59*F59) | MB59: basins, etc. May consist of silt, vegetation, wreckage, etc., causing flow
C60: =IF(ISBLANK(B60)," ",VLOOKUP(B60,LZ60:MD1272,3,FALSE)) | D60: =IF(ISBLANK(B60)," ",VLOOKUP(B60,LZ60:MD1272,4,FALSE)) | E60: =IF(ISBLANK(B60)," ",VLOOKUP(B60,LZ60:MD1272,2,FALSE)) | G60: =IF(ISERROR(D60*F60)," ",D60*F60) | MB60: problems.
C61: =IF(ISBLANK(B61)," ",VLOOKUP(B61,LZ61:MD1273,3,FALSE)) | D61: =IF(ISBLANK(B61)," ",VLOOKUP(B61,LZ61:MD1273,4,FALSE)) | E61: =IF(ISBLANK(B61)," ",VLOOKUP(B61,LZ61:MD1273,2,FALSE)) | G61: =IF(ISERROR(D61*F61)," ",D61*F61)
C62: =IF(ISBLANK(B62)," ",VLOOKUP(B62,LZ62:MD1274,3,FALSE)) | D62: =IF(ISBLANK(B62)," ",VLOOKUP(B62,LZ62:MD1274,4,FALSE)) | E62: =IF(ISBLANK(B62)," ",VLOOKUP(B62,LZ62:MD1274,2,FALSE)) | G62: =IF(ISERROR(D62*F62)," ",D62*F62)
C63: =IF(ISBLANK(B63)," ",VLOOKUP(B63,LZ63:MD1275,3,FALSE)) | D63: =IF(ISBLANK(B63)," ",VLOOKUP(B63,LZ63:MD1275,4,FALSE)) | E63: =IF(ISBLANK(B63)," ",VLOOKUP(B63,LZ63:MD1275,2,FALSE)) | G63: =IF(ISERROR(D63*F63)," ",D63*F63)
C64: =IF(ISBLANK(B64)," ",VLOOKUP(B64,LZ64:MD1276,3,FALSE)) | D64: =IF(ISBLANK(B64)," ",VLOOKUP(B64,LZ64:MD1276,4,FALSE)) | E64: =IF(ISBLANK(B64)," ",VLOOKUP(B64,LZ64:MD1276,2,FALSE)) | G64: =IF(ISERROR(D64*F64)," ",D64*F64) | LZ64: 1021 | MA64: CY | MB64: DEBRIS (CRADLE TO GRAVE REMOVAL) | MC64: $ 20.00
C65: =IF(ISBLANK(B65)," ",VLOOKUP(B65,LZ65:MD1277,3,FALSE)) | D65: =IF(ISBLANK(B65)," ",VLOOKUP(B65,LZ65:MD1277,4,FALSE)) | E65: =IF(ISBLANK(B65)," ",VLOOKUP(B65,LZ65:MD1277,2,FALSE)) | G65: =IF(ISERROR(D65*F65)," ",D65*F65) | MB65: Applicant contracts for "cradle to grave", removal of debris from Right-of-
C66: =IF(ISBLANK(B66)," ",VLOOKUP(B66,LZ66:MD1278,3,FALSE)) | D66: =IF(ISBLANK(B66)," ",VLOOKUP(B66,LZ66:MD1278,4,FALSE)) | E66: =IF(ISBLANK(B66)," ",VLOOKUP(B66,LZ66:MD1278,2,FALSE)) | G66: =IF(ISERROR(D66*F66)," ",D66*F66) | MB66: W ay, chipping and disposal. (Does not include tipping fees)
C67: =IF(ISBLANK(B67)," ",VLOOKUP(B67,LZ67:MD1279,3,FALSE)) | D67: =IF(ISBLANK(B67)," ",VLOOKUP(B67,LZ67:MD1279,4,FALSE)) | E67: =IF(ISBLANK(B67)," ",VLOOKUP(B67,LZ67:MD1279,2,FALSE)) | G67: =IF(ISERROR(D67*F67)," ",D67*F67) | LZ67: 1015 | MA67: CY | MB67: DEBRIS (TREES & LIMBS, SCATTERED | MC67: $ 6.00
C68: =IF(ISBLANK(B68)," ",VLOOKUP(B68,LZ68:MD1280,3,FALSE)) | D68: =IF(ISBLANK(B68)," ",VLOOKUP(B68,LZ68:MD1280,4,FALSE)) | E68: =IF(ISBLANK(B68)," ",VLOOKUP(B68,LZ68:MD1280,2,FALSE)) | G68: =IF(ISERROR(D68*F68)," ",D68*F68) | MB68: Broken trees and limbs scattered around affected area.
C69: =IF(ISBLANK(B69)," ",VLOOKUP(B69,LZ69:MD1281,3,FALSE)) | D69: =IF(ISBLANK(B69)," ",VLOOKUP(B69,LZ69:MD1281,4,FALSE)) | E69: =IF(ISBLANK(B69)," ",VLOOKUP(B69,LZ69:MD1281,2,FALSE)) | G69: =IF(ISERROR(D69*F69)," ",D69*F69) | LZ69: 1016 | MA69: MI | MB69: DEBRIS (W INDBLOW N TREES ALONG ROW -MAXIMUM DENSITY) | MC69: $ 5,000.00
C70: =IF(ISBLANK(B70)," ",VLOOKUP(B70,LZ70:MD1282,3,FALSE)) | D70: =IF(ISBLANK(B70)," ",VLOOKUP(B70,LZ70:MD1282,4,FALSE)) | E70: =IF(ISBLANK(B70)," ",VLOOKUP(B70,LZ70:MD1282,2,FALSE)) | G70: =IF(ISERROR(D70*F70)," ",D70*F70) | MB70: In a major disaster there may be extensive debris from trees and limbs
C71: =IF(ISBLANK(B71)," ",VLOOKUP(B71,LZ71:MD1283,3,FALSE)) | D71: =IF(ISBLANK(B71)," ",VLOOKUP(B71,LZ71:MD1283,4,FALSE)) | E71: =IF(ISBLANK(B71)," ",VLOOKUP(B71,LZ71:MD1283,2,FALSE)) | G71: =IF(ISERROR(D71*F71)," ",D71*F71) | MB71: over several miles of roads or streets.
C72: =IF(ISBLANK(B72)," ",VLOOKUP(B72,LZ72:MD1284,3,FALSE)) | D72: =IF(ISBLANK(B72)," ",VLOOKUP(B72,LZ72:MD1284,4,FALSE)) | E72: =IF(ISBLANK(B72)," ",VLOOKUP(B72,LZ72:MD1284,2,FALSE)) | G72: =IF(ISERROR(D72*F72)," ",D72*F72) | LZ72: 1017 | MA72: CY | MB72: DEBRIS LOADED AND HAULED TO TDRS | MC72: $ 11.25
C73: =IF(ISBLANK(B73)," ",VLOOKUP(B73,LZ73:MD1285,3,FALSE)) | D73: =IF(ISBLANK(B73)," ",VLOOKUP(B73,LZ73:MD1285,4,FALSE)) | E73: =IF(ISBLANK(B73)," ",VLOOKUP(B73,LZ73:MD1285,2,FALSE)) | G73: =IF(ISERROR(D73*F73)," ",D73*F73) | MB73: Debris loaded and hauled to TDRS (Temporary Debris Reduction Site)
C74: =IF(ISBLANK(B74)," ",VLOOKUP(B74,LZ74:MD1286,3,FALSE)) | D74: =IF(ISBLANK(B74)," ",VLOOKUP(B74,LZ74:MD1286,4,FALSE)) | E74: =IF(ISBLANK(B74)," ",VLOOKUP(B74,LZ74:MD1286,2,FALSE)) | G74: =IF(ISERROR(D74*F74)," ",D74*F74) | LZ74: 1020 | MA74: CY | MB74: DEBRIS (W ATERWAY STRUCTURE) | MC74: $ 8.00
C75: =IF(ISBLANK(B75)," ",VLOOKUP(B75,LZ75:MD1287,3,FALSE)) | D75: =IF(ISBLANK(B75)," ",VLOOKUP(B75,LZ75:MD1287,4,FALSE)) | E75: =IF(ISBLANK(B75)," ",VLOOKUP(B75,LZ75:MD1287,2,FALSE)) | G75: =IF(ISERROR(D75*F75)," ",D75*F75) | MB75: Debris that has been deposited by floodwater on levees, dams,settling
C76: =IF(ISBLANK(B76)," ",VLOOKUP(B76,LZ76:MD1288,3,FALSE)) | D76: =IF(ISBLANK(B76)," ",VLOOKUP(B76,LZ76:MD1288,4,FALSE)) | E76: =IF(ISBLANK(B76)," ",VLOOKUP(B76,LZ76:MD1288,2,FALSE)) | G76: =IF(ISERROR(D76*F76)," ",D76*F76) | MB76: basins, etc. May consist of silt, vegetation, wreckage, etc., causing flow
C77: =IF(ISBLANK(B77)," ",VLOOKUP(B77,LZ77:MD1289,3,FALSE)) | D77: =IF(ISBLANK(B77)," ",VLOOKUP(B77,LZ77:MD1289,4,FALSE)) | E77: =IF(ISBLANK(B77)," ",VLOOKUP(B77,LZ77:MD1289,2,FALSE)) | G77: =IF(ISERROR(D77*F77)," ",D77*F77) | MB77: problems.
C78: =IF(ISBLANK(B78)," ",VLOOKUP(B78,LZ78:MD1290,3,FALSE)) | D78: =IF(ISBLANK(B78)," ",VLOOKUP(B78,LZ78:MD1290,4,FALSE)) | E78: =IF(ISBLANK(B78)," ",VLOOKUP(B78,LZ78:MD1290,2,FALSE)) | G78: =IF(ISERROR(D78*F78)," ",D78*F78)
C79: =IF(ISBLANK(B79)," ",VLOOKUP(B79,LZ79:MD1291,3,FALSE)) | D79: =IF(ISBLANK(B79)," ",VLOOKUP(B79,LZ79:MD1291,4,FALSE)) | E79: =IF(ISBLANK(B79)," ",VLOOKUP(B79,LZ79:MD1291,2,FALSE)) | G79: =IF(ISERROR(D79*F79)," ",D79*F79)
C80: =IF(ISBLANK(B80)," ",VLOOKUP(B80,LZ80:MD1292,3,FALSE)) | D80: =IF(ISBLANK(B80)," ",VLOOKUP(B80,LZ80:MD1292,4,FALSE)) | E80: =IF(ISBLANK(B80)," ",VLOOKUP(B80,LZ80:MD1292,2,FALSE)) | G80: =IF(ISERROR(D80*F80)," ",D80*F80)
C81: =IF(ISBLANK(B81)," ",VLOOKUP(B81,LZ81:MD1293,3,FALSE)) | D81: =IF(ISBLANK(B81)," ",VLOOKUP(B81,LZ81:MD1293,4,FALSE)) | E81: =IF(ISBLANK(B81)," ",VLOOKUP(B81,LZ81:MD1293,2,FALSE)) | G81: =IF(ISERROR(D81*F81)," ",D81*F81) | LZ81: 1021 | MA81: CY | MB81: DEBRIS (CRADLE TO GRAVE REMOVAL) | MC81: $ 20.00
C82: =IF(ISBLANK(B82)," ",VLOOKUP(B82,LZ82:MD1294,3,FALSE)) | D82: =IF(ISBLANK(B82)," ",VLOOKUP(B82,LZ82:MD1294,4,FALSE)) | E82: =IF(ISBLANK(B82)," ",VLOOKUP(B82,LZ82:MD1294,2,FALSE)) | G82: =IF(ISERROR(D82*F82)," ",D82*F82) | MB82: Applicant contracts for "cradle to grave", removal of debris from Right-of-
C83: =IF(ISBLANK(B83)," ",VLOOKUP(B83,LZ83:MD1295,3,FALSE)) | D83: =IF(ISBLANK(B83)," ",VLOOKUP(B83,LZ83:MD1295,4,FALSE)) | E83: =IF(ISBLANK(B83)," ",VLOOKUP(B83,LZ83:MD1295,2,FALSE)) | G83: =IF(ISERROR(D83*F83)," ",D83*F83) | MB83: W ay, chipping and disposal. (Does not include tipping fees)
C84: =IF(ISBLANK(B84)," ",VLOOKUP(B84,LZ84:MD1279,3,FALSE)) | D84: =IF(ISBLANK(B84)," ",VLOOKUP(B84,LZ84:MD1279,4,FALSE)) | E84: =IF(ISBLANK(B84)," ",VLOOKUP(B84,LZ84:MD1279,2,FALSE)) | G84: =IF(ISERROR(D84*F84)," ",D84*F84) | LZ84: 1022 | MA84: CY | MB84: DEBRIS FROM RIGHT-OF-W AY AND CHIPS | MC84: $ 11.25
C85: =IF(ISBLANK(B85)," ",VLOOKUP(B85,Estimate!LZ88:MC923,3,TRUE)) | E85: Grand Total | G85: =SUM(G11:G84) -> 0 | MB85: Trees, broken uprooted 19-36" Diameter.
C86: =IF(ISBLANK(B86)," ",VLOOKUP(B86,Estimate!LZ89:MC923,3,TRUE)) | LZ86: 1033 | MA86: EA | MB86: DEBRIS (REMOVAL OF HANGERS FROM RIGHT-OF-W AY) | MC86: $ 72.00
C87: =IF(ISBLANK(B87)," ",VLOOKUP(B87,Estimate!LZ90:MC923,3,TRUE)) | MB87: Removal of hangers from right-of-way. (Cost is for per tree)
C88: =IF(ISBLANK(B88)," ",VLOOKUP(B88,Estimate!LZ91:MC923,3,TRUE)) | LZ88: 1034 | MA88: EA | MB88: HAZARDOUS TREE REMOVAL: 6" TO 11.99" Debris, hazardous tree removal, CROWN must be damage more than 50%. | MC88: $ 165.00
C89: =IF(ISBLANK(B89)," ",VLOOKUP(B89,Estimate!LZ92:MC923,3,TRUE)) | LZ89: 1035 | MA89: EA | MB89: HAZARDOUS TREE REMOVAL, 12" TO 23.99" Debris, hazardous tree removal, CROW N must be damage more than | MC89: $ 475.00
C90: =IF(ISBLANK(B90)," ",VLOOKUP(B90,Estimate!LZ93:MC923,3,TRUE)) | MB90: 50%.
C91: =IF(ISBLANK(B91)," ",VLOOKUP(B91,Estimate!LZ94:MC923,3,TRUE)) | LZ91: 1036 | MA91: EA | MB91: HAZARDOUS TREE REMOVAL: 24" TO 35.99" | MC91: $ 800.00
C92: =IF(ISBLANK(B92)," ",VLOOKUP(B92,Estimate!LZ95:MC923,3,TRUE)) | MB92: Debris, hazardous tree removal. CROW N must be damage more than
C93: =IF(ISBLANK(B93)," ",VLOOKUP(B93,Estimate!LZ96:MC923,3,TRUE)) | MB93: 50%
C94: =IF(ISBLANK(B94)," ",VLOOKUP(B94,Estimate!LZ97:MC923,3,TRUE)) | LZ94: 1037 | MA94: EA | MB94: HAZARDOUS TREE REMOVAL: 36" TO 47.99" | MC94: $ 1,000.00
C95: =IF(ISBLANK(B95)," ",VLOOKUP(B95,Estimate!LZ98:MC923,3,TRUE)) | MB95: Debris, hazardous tree removal. CROW N must be damage more than
C96: =IF(ISBLANK(B96)," ",VLOOKUP(B96,Estimate!LZ99:MC923,3,TRUE)) | MB96: 50%.
C97: =IF(ISBLANK(B97)," ",VLOOKUP(B97,Estimate!LZ100:MC923,3,TRUE)) | LZ97: 1038 | MA97: EA | MB97: HAZARDOUS TREE REMOVAL: 48" TO 55.99" | MC97: $ 2,100.00
C98: =IF(ISBLANK(B98)," ",VLOOKUP(B98,Estimate!LZ101:MC923,3,TRUE)) | MB98: Debris, hazardous tree removal. CROW N must be damage more than
C99: =IF(ISBLANK(B99)," ",VLOOKUP(B99,Estimate!LZ102:MC923,3,TRUE)) | MB99: 50%
C100: =IF(ISBLANK(B100)," ",VLOOKUP(B100,Estimate!LZ103:MC923,3,TRUE)) | LZ100: 1039 | MA100: EA | MB100: HAZARDOUS TREE REMOVAL: 56" AND GREATER | MC100: $ 2,600.00
C101: =IF(ISBLANK(B101)," ",VLOOKUP(B101,Estimate!LZ104:MC923,3,TRUE)) | MB101: Debris, hazardous tree removal. CROW N must be damage more than
C102: =IF(ISBLANK(B102)," ",VLOOKUP(B102,Estimate!LZ105:MC923,3,TRUE)) | MB102: 50%.
...

Sheet Summary Sheet
A1: DEPARTMENT OF HOMELAND SECURITY
A2: FEDERAL EMERGENCY MANAGEMENT
A3: PRELIMINARY DAMAGE ASSESSMENT SUMMARY
A5: Part 1 - Applicant Information
A6: County | D6: Potential Applicant/Public Entity | G6: Name of Local Contact | J6: Contact Phone #
A7: Bosque | D7: Multiple | G7: Multiple (individual sheets) | J7: (various)
A8: Population | C8: Total Budget | E8: Maintenance Budget | G8: Insured | J8: Date
G9: Needs Mitigation
A10: Part II - Site Estimate Summary
A11: Category | C11: Critical Facilities and Other Damages | E11: Inspected | G11: Projected | I11: Total
E12: # of Sites | F12: Cost | G12: # of Sites | H12: Cost | I12: # of Sites | J12: Total Cost
A13: A | B13: Debris | E13: 1 | F13: ='Valley Mills'!K20 -> 3080 | I13: =E13+G13 -> 1 | J13: =F13+H13 -> 3080
A14: B | B14: Prot. Measures | I14: =E14+G14 -> 0 | J14: =F14+H14 -> 0
B15: Cat A & B Emergency work sub-total | J15: =J13+J14 -> 3080
A17: C | B17: Roads and Bridges | C17: Bridge | I17: =E17+G17 -> 0
C18: Roadway | E18: 9 | F18: ='Bosque Co'!K20+'Bosque Co'!K30+'Bosque Co'!K40+'Bosque Co'!K50+'Bosque Co (2)'!K20+Clifton!K20+Clifton!K30+Clifton!K40+Clifton!K50 -> 165925 | G18: 4 | H18: =9000+500+1200+10500 -> 21200 | I18: =E18+G18 -> 13 | J18: =F18+H18 -> 187125
C19: Aggregate surface loss only | I19: =E19+G19 -> 0 | J19: =F19+H19 -> 0
B20: Cat C Sub-total | J20: =J17+J18+J19 -> 187125
A22: D | B22: Water Control Facilities | C22: Dam | E22: 1 | F22: ='Clifton(2)'!K20 -> 22500 | I22: =E22+G22 -> 1 | J22: =F22+H22 -> 22500
C23: Levee | I23: =E23+G23 -> 0 | J23: =F23+H23 -> 0
C24: Drainage Channel | I24: =E24+G24 -> 0
B25: Cat D Sub-total | J25: =J22+J23+J24 -> 22500
A27: E | B27: Public Buildings | I27: =E27+G27 -> 0
D28: Contents | I28: =E28+G28 -> 0 | J28: =F28+H28 -> 0
I29: =E29+G29 -> 0 | J29: =F29+H29 -> 0
B30: Cat E Sub-total | J30: =J27+J28+J29 -> 0
A32: F | B32: Public Utilities | C32: Water Treatment | I32: =E32+G32 -> 0 | J32: =F32+H32 -> 0
C33: Water Utility | I33: =E33+G33 -> 0 | J33: =F33+H33 -> 0
C34: Sewage Treatment | I34: =E34+G34 -> 0 | J34: =F34+H34 -> 0
B35: Cat F Sub-total | J35: =J32+J33+J34 -> 0
A37: G | B37: Other Recreation | C37: Railroad | I37: =E37+G37 -> 0 | J37: =F37+H37 -> 0
C38: Fence | I38: =E38+G38 -> 0 | J38: =F38+H38 -> 0
I39: =E39+G39 -> 0
B40: Cat G Sub-total | J40: =J37+J38+J39 -> 0
A42: Emergency and Permanent Work Total
H44: GRAND TOTAL | J44: =J15+J20+J25+J30+J35+J40 -> 212705
A46: Part lll - Disaster Impacts (Use separate sheets if necessary) | L46: Restricted access for emergency responder vehicles, public school transportation and local residence.
A47: A. General Impact | L47: Prevailing damages restricting access proposes a threat to public health and safety
A48: 1. Briefly describe damages which constitute a health and safety hazard to the general public.
L49: Emergency vehicles, school bus and postal services unable to perform mission due to road and bridge wash out.
A51: 2. Population adversely affected directly or indirectly by loss of public facilities or damages.
L52: Road and bridge washed out.
A55: 3. What economic activities are adversely affected by the loss of public facilities or damages?
L56: Population unable to transit from home to work, economic impact for local businesses to distribute materials, food
L57: products, etc.
A58: B. Response Capability (use other side of page when necessary)
A59: 1. Can the Applicant respond and recover from the damages quickly and without degradation of public services? Please explain.
L60: Emergency repairs have been made to open roads and bridges to vehicle traffic.
A62: C. Impact on Public Services if Declaration Not Made (use other side of page when necessary)
A63: 1. Discuss the need, if any to defer permanent repairs and the impact on ongoing services.
L64: Financial burden to applicant and slow permanent repair timeframe.
A66: Signature of Inspector | E66: Name of Inspector | G66: Agency | I66: Phone Number
E67: Vernon Lansford | G67: FEMA | I67: 225-910-5272

Sheet Bosque Co
A1: Federal Emergency Management Agency | L1: Date
A2: Preliminary Damage Assessment Site Estimate | L2: 42557
A3: Part 1 - Applicant Information
A4: County | C4: Name Of Applicant | G4: Name Of Local Contact | L4: Contact Phone #
A5: Bosque | C5: Bosque County | G5: Tim Jeske | L5: 254-230-6622
A6: Part 2 - Site Information
A7: Key For Damage Category (Use appropriate letters in the "category" blocks below)
B8: a. Debris Removal | E8: d. Water Control Facilities | I8: g. Other Recreation
B9: b. Protective Measures | E9: e. Public Buildings
B10: c. Roads And Bridges | E10: f. Public Utilities
A11: Site No. | B11: Category | C11: Location (Use map location, address, etc.): | G11: CR-3105 | L11: GPS
A12: 1 | B12: C | L12: 31.854218
L13: -97.618797
A14: Description Of Damage
A15: Culvert with headwall collapsed on downstream end of cmp. Hand stacked headwall with concrete top. Minor damage on inlet end of cmp.
A19: Impact: | B19: Minor | H19: % Complete | K19: Cost Estimate
H20: 0 | K20: 5000
A21: Site No. | B21: Category | C21: Location (Use map location, address, etc.): | G21: CR-1190 (Site 1) | L21: GPS
A22: 2 | B22: C | L22: 32.111477
L23: -97.494183
A24: Description Of Damage
A25: Chip and Seal roadway deteriorating after water sat on roadway for 12-21 days.
A29: Impact: | B29: Minor | H29: % Complete | K29: Cost Estimate
H30: 0 | K30: 25000
A31: Site No. | B31: Category | C31: Location (Use map location, address, etc.): | G31: CR-1190 (Site 2) | L31: GPS
A32: 3 | B32: C | L32: 31.078793
L33: -97.504822
A34: Description Of Damage
A35: Chip and Seal roadway deteriorating after water sat on roadway for 12-21 days.
A39: Impact: | B39: Minor | H39: % Complete | K39: Cost Estimate
H40: 0 | K40: 2000
A41: Site No. | B41: Category | C41: Location (Use map location, address, etc.): | G41: CR-3660 | L41: GPS
A42: 4 | B42: C | L42: 31.745107
L43: -97.298062
A44: Description Of Damage
A45: Bridge shoulder washed out. Note, Applicant is not claiming the debris. The 2 cmps and box culvert did not sustain any damage.
A49: Impact: | B49: Moderate | H49: % Complete | K49: Cost Estimate
H50: 0 | K50: 20000
A51: Name Of Inspector | D51: Agency | G51: Phone No. Office | K51: Phone No.CELL
A52: ='Summary Sheet'!E67 -> Vernon Lansford | D52: ='Summary Sheet'!G67 -> FEMA | K52: ='Summary Sheet'!I67 -> 225-910-5272
A54: FEMA Form 90-81, Jan 84 | G54: GRAND TOTAL SHEET 2 | K54: =+K20+K30+K40+K50 -> 52000
A56: 1. Asphalt (3100) $5.30/SY/IN | D56: 8. Grading Roads (3072) $0.10/SY | G56: 15. CMP 48" (3358) $62/LF | K56: 22. Auto Police (8073) $14.35/HR
A57: 2. Aggregate Surface (3011) $13/CY | D57: 9. Rip Rap (3250) $35/CY | G57: 16. CMP 60" (3354) $76/LF | K57: 23. CMD Center (9999) $339/HR
A58: 3. Aggregate Base (3091) $19.50/CY | D58: 10. Bridge Railing 3" (3294) $35/LF | G58: 17. CMP 72" (3354) $115/LF | K58: 24. Helo, Rescue (9999) $6277/HR
A59: 4. Chip & Seal Single (3080) $1.55/SY | D59: 11. Debris C&D (1012) $3.50/CY | G59: 18. CMP 120" (3364) $175/LF | K59: 25. Boat RBS (9999) $323/HR
A60: 5. Chip & Seal Double (3081) $2.79/SY | D60: 12. Debris Veg. (1015) $6/CY | G60: 19. Pickup (8804) $19.90/HR | K60: 26. Boat Utility (9999) $980/HR
A61: 6. Chip & Seal Triple (3082) $4.03/SY | D61: 13. CMP 24" (3354) $30/LF | G61: 20. Trailer, 30 T (8600) $9.90/HR | K61: 27. Person, Vol. (9999) $10/HR
A62: 7. Fill Unclas (3020) $7/CY | D62: 14. CMP 36" (3354) $41/LF | G62: 21. Bus, Large (8182) $30.00/HR | K62: 28. Canine & Handler (9999) $30/HR

Sheet Bosque Co (2)
A1: Federal Emergency Management Agency | L1: Date
A2: Preliminary Damage Assessment Site Estimate | L2: 42557
A3: Part 1 - Applicant Information
A4: County | C4: Name Of Applicant | G4: Name Of Local Contact | L4: Contact Phone #
A5: Bosque | C5: Bosque County | G5: Tim Jeske | L5: 254-230-6622
A6: Part 2 - Site Information
A7: Key For Damage Category (Use appropriate letters in the "category" blocks below)
B8: a. Debris Removal | E8: d. Water Control Facilities | I8: g. Other Recreation
B9: b. Protective Measures | E9: e. Public Buildings
B10: c. Roads And Bridges | E10: f. Public Utilities
A11: Site No. | B11: Category | C11: Location (Use map location, address, etc.): | G11: ROADS | L11: GPS | O11: * NEEDS MITIGATION
A12: 5 | B12: C | L12: 31.820868
L13: -97.486504
A14: Description Of Damage
A15: Low water crossing undermined during the event.
A19: Impact: | B19: Minor, inconvenience and hazard to motorist | H19: % Complete | K19: Cost Estimate
H20: 0 | K20: 28000
A21: Site No. | B21: Category | C21: Location (Use map location, address, etc.): | L21: GPS
A24: Description Of Damage
A29: Impact: | H29: % Complete | K29: Cost Estimate
A31: Site No. | B31: Category | C31: Location (Use map location, address, etc.): | L31: GPS
A34: Description Of Damage
A39: Impact: | H39: % Complete | K39: Cost Estimate
A41: Site No. | B41: Category | C41: Location (Use map location, address, etc.): | L41: GPS
A44: Description Of Damage
A49: Impact: | H49: % Complete | K49: Cost Estimate
A51: Name Of Inspector | D51: Agency | G51: Phone No. Office | K51: Phone No.CELL
A52: ='Summary Sheet'!E67 -> Vernon Lansford | D52: ='Summary Sheet'!G67 -> FEMA | G52: =IF('Bosque Co'!G52=0,"",'Bosque Co'!G52) | K52: ='Summary Sheet'!I67 -> 225-910-5272
A54: FEMA Form 90-81, Jan 84 | G54: GRAND TOTAL SHEET 2 | K54: =+K20+K30+K40+K50 -> 28000
A56: 1. Asphalt (3100) $5.30/SY/IN | D56: 8. Grading Roads (3072) $0.10/SY | G56: 15. CMP 48" (3358) $62/LF | K56: 22. Auto Police (8073) $14.35/HR
A57: 2. Aggregate Surface (3011) $13/CY | D57: 9. Rip Rap (3250) $35/CY | G57: 16. CMP 60" (3354) $76/LF | K57: 23. CMD Center (9999) $339/HR
A58: 3. Aggregate Base (3091) $19.50/CY | D58: 10. Bridge Railing 3" (3294) $35/LF | G58: 17. CMP 72" (3354) $115/LF | K58: 24. Helo, Rescue (9999) $6277/HR
A59: 4. Chip & Seal Single (3080) $1.55/SY | D59: 11. Debris C&D (1012) $3.50/CY | G59: 18. CMP 120" (3364) $175/LF | K59: 25. Boat RBS (9999) $323/HR
A60: 5. Chip & Seal Double (3081) $2.79/SY | D60: 12. Debris Veg. (1015) $6/CY | G60: 19. Pickup (8804) $19.90/HR | K60: 26. Boat Utility (9999) $980/HR
A61: 6. Chip & Seal Triple (3082) $4.03/SY | D61: 13. CMP 24" (3354) $30/LF | G61: 20. Trailer, 30 T (8600) $9.90/HR | K61: 27. Person, Vol. (9999) $10/HR
A62: 7. Fill Unclas (3020) $7/CY | D62: 14. CMP 36" (3354) $41/LF | G62: 21. Bus, Large (8182) $30.00/HR | K62: 28. Canine & Handler (9999) $30/HR

Sheet Clifton
A1: Federal Emergency Management Agency | L1: Date
A2: Preliminary Damage Assessment Site Estimate | L2: 42557
A3: Part 1 - Applicant Information
A4: County | C4: Name Of Applicant | G4: Name Of Local Contact | L4: Contact Phone #
A5: Bosque | C5: City of Clifton | G5: Ashley Able | L5: 254-675-8337
A6: Part 2 - Site Information
A7: Key For Damage Category (Use appropriate letters in the "category" blocks below)
B8: a. Debris Removal | E8: d. Water Control Facilities | I8: g. Other Recreation
B9: b. Protective Measures | E9: e. Public Buildings
B10: c. Roads And Bridges | E10: f. Public Utilities
A11: Site No. | B11: Category | C11: Location (Use map location, address, etc.): | G11: Mountain Oak Circle | L11: GPS
A12: 1 | B12: C | L12: 31.77587
L13: -97.59748
A14: Description Of Damage
A15: Additional loss of asphalt and road base from event. Site previously damaged.
A19: Impact: | B19: Barricaded | H19: % Complete | K19: Cost Estimate
H20: 0 | K20: 28435
A21: Site No. | B21: Category | C21: Location (Use map location, address, etc.): | G21: White St starting at Ridgeview, South | L21: GPS
A22: 2 | B22: C | L22: 31.77634
L23: -97.59644
A24: Description Of Damage
A25: Additional loss of asphalt and road base from event. Site previously damaged.
A29: Impact: | B29: Minor inconvenience to motorist, base material only. | H29: % Complete | K29: Cost Estimate
H30: 0 | K30: 32500 | O30: =3500/700 -> 5 | P30: =O30*(7200-700) -> 32500
A31: Site No. | B31: Category | C31: Location (Use map location, address, etc.): | G31: 13th St | L31: GPS
A32: 3 | B32: C | L32: 31.77583
L33: -97.58194
A34: Description Of Damage
A35: Additional loss of asphalt and road base from event. Site previously damaged.
A39: Impact: | B39: Minor inconvenience to motorist, base material only. | H39: % Complete | K39: Cost Estimate
H40: 0 | K40: =17365-14875 -> 2490
A41: Site No. | B41: Category | C41: Location (Use map location, address, etc.): | G41: 21st St | L41: GPS
A42: 4 | B42: C | L42: 31.77139
L43: -97.58056
A44: Description Of Damage
A45: Additional damage to road base from event. Alligator cracking where there were none from earlier events. Road base very soft, Heavy vehicles have fallen through. Site previously damaged.
A49: Impact: | B49: Minor inconvenience to motorist, base material only. | H49: % Complete | K49: Cost Estimate
H50: 0 | K50: 22500
A51: Name Of Inspector | D51: Agency | G51: Phone No. Office | K51: Phone No.CELL
A52: ='Summary Sheet'!E67 -> Vernon Lansford | D52: ='Summary Sheet'!G67 -> FEMA | G52: =IF('Bosque Co'!G52=0,"",'Bosque Co'!G52) | K52: ='Summary Sheet'!I67 -> 225-910-5272
A54: FEMA Form 90-81, Jan 84 | G54: GRAND TOTAL SHEET 2 | K54: =+K20+K30+K40+K50 -> 85925
A56: 1. Asphalt (3100) $5.30/SY/IN | D56: 8. Grading Roads (3072) $0.10/SY | G56: 15. CMP 48" (3358) $62/LF | K56: 22. Auto Police (8073) $14.35/HR
A57: 2. Aggregate Surface (3011) $13/CY | D57: 9. Rip Rap (3250) $35/CY | G57: 16. CMP 60" (3354) $76/LF | K57: 23. CMD Center (9999) $339/HR
A58: 3. Aggregate Base (3091) $19.50/CY | D58: 10. Bridge Railing 3" (3294) $35/LF | G58: 17. CMP 72" (3354) $115/LF | K58: 24. Helo, Rescue (9999) $6277/HR
A59: 4. Chip & Seal Single (3080) $1.55/SY | D59: 11. Debris C&D (1012) $3.50/CY | G59: 18. CMP 120" (3364) $175/LF | K59: 25. Boat RBS (9999) $323/HR
A60: 5. Chip & Seal Double (3081) $2.79/SY | D60: 12. Debris Veg. (1015) $6/CY | G60: 19. Pickup (8804) $19.90/HR | K60: 26. Boat Utility (9999) $980/HR
A61: 6. Chip & Seal Triple (3082) $4.03/SY | D61: 13. CMP 24" (3354) $30/LF | G61: 20. Trailer, 30 T (8600) $9.90/HR | K61: 27. Person, Vol. (9999) $10/HR
A62: 7. Fill Unclas (3020) $7/CY | D62: 14. CMP 36" (3354) $41/LF | G62: 21. Bus, Large (8182) $30.00/HR | K62: 28. Canine & Handler (9999) $30/HR

Sheet Clifton(2)
A1: Federal Emergency Management Agency | L1: Date
A2: Preliminary Damage Assessment Site Estimate | L2: 42557
A3: Part 1 - Applicant Information
A4: County | C4: Name Of Applicant | G4: Name Of Local Contact | L4: Contact Phone #
A5: Bosque | C5: City of Clifton | G5: Ashley Able | L5: 254-675-8337
A6: Part 2 - Site Information
A7: Key For Damage Category (Use appropriate letters in the "category" blocks below)
B8: a. Debris Removal | E8: d. Water Control Facilities | I8: g. Other Recreation
B9: b. Protective Measures | E9: e. Public Buildings
B10: c. Roads And Bridges | E10: f. Public Utilities
A11: Site No. | B11: Category | C11: Location (Use map location, address, etc.): | G11: Dam/Weir complex | L11: GPS | O11: * NEEDS MITIGATION
A12: 5 | B12: D | C12: On Bosque River off of CR-3112 | L12: 31.79478
L13: -97.57643
A14: Description Of Damage
A15: Additional erosion of complex and loss of Large Rip Rap from the event. Site damaged in Dr-4245-TX & Dr-4269-TX.
A19: Impact: | B19: High | H19: % Complete | K19: Cost Estimate
H20: 0 | K20: =104500-82000 -> 22500
A21: Site No. | B21: Category | C21: Location (Use map location, address, etc.): | L21: GPS
A24: Description Of Damage
A29: Impact: | H29: % Complete | K29: Cost Estimate
A31: Site No. | B31: Category | C31: Location (Use map location, address, etc.): | L31: GPS
A34: Description Of Damage
A39: Impact: | H39: % Complete | K39: Cost Estimate
A41: Site No. | B41: Category | C41: Location (Use map location, address, etc.): | L41: GPS
A44: Description Of Damage
A49: Impact: | H49: % Complete | K49: Cost Estimate
A51: Name Of Inspector | D51: Agency | G51: Phone No. Office | K51: Phone No.CELL
A52: ='Summary Sheet'!E67 -> Vernon Lansford | D52: ='Summary Sheet'!G67 -> FEMA | G52: =IF('Bosque Co'!G52=0,"",'Bosque Co'!G52) | K52: ='Summary Sheet'!I67 -> 225-910-5272
A54: FEMA Form 90-81, Jan 84 | G54: GRAND TOTAL SHEET 2 | K54: =+K20+K30+K40+K50 -> 22500
A56: 1. Asphalt (3100) $5.30/SY/IN | D56: 8. Grading Roads (3072) $0.10/SY | G56: 15. CMP 48" (3358) $62/LF | K56: 22. Auto Police (8073) $14.35/HR
A57: 2. Aggregate Surface (3011) $13/CY | D57: 9. Rip Rap (3250) $35/CY | G57: 16. CMP 60" (3354) $76/LF | K57: 23. CMD Center (9999) $339/HR
A58: 3. Aggregate Base (3091) $19.50/CY | D58: 10. Bridge Railing 3" (3294) $35/LF | G58: 17. CMP 72" (3354) $115/LF | K58: 24. Helo, Rescue (9999) $6277/HR
A59: 4. Chip & Seal Single (3080) $1.55/SY | D59: 11. Debris C&D (1012) $3.50/CY | G59: 18. CMP 120" (3364) $175/LF | K59: 25. Boat RBS (9999) $323/HR
A60: 5. Chip & Seal Double (3081) $2.79/SY | D60: 12. Debris Veg. (1015) $6/CY | G60: 19. Pickup (8804) $19.90/HR | K60: 26. Boat Utility (9999) $980/HR
A61: 6. Chip & Seal Triple (3082) $4.03/SY | D61: 13. CMP 24" (3354) $30/LF | G61: 20. Trailer, 30 T (8600) $9.90/HR | K61: 27. Person, Vol. (9999) $10/HR
A62: 7. Fill Unclas (3020) $7/CY | D62: 14. CMP 36" (3354) $41/LF | G62: 21. Bus, Large (8182) $30.00/HR | K62: 28. Canine & Handler (9999) $30/HR

Sheet Valley Mills
A1: Federal Emergency Management Agency | L1: Date
A2: Preliminary Damage Assessment Site Estimate
A3: Part 1 - Applicant Information
A4: County | C4: Name Of Applicant | G4: Name Of Local Contact | L4: Contact Phone #
A5: Bosque | C5: City of Valley Mills
A6: Part 2 - Site Information
A7: Key For Damage Category (Use appropriate letters in the "category" blocks below)
B8: a. Debris Removal | E8: d. Water Control Facilities | I8: g. Other Recreation
B9: b. Protective Measures | E9: e. Public Buildings
B10: c. Roads And Bridges | E10: f. Public Utilities
A11: Site No. | B11: Category | C11: Location (Use map location, address, etc.): | G11: Staging Site | L11: GPS | O11: * NEEDS MITIGATION
A12: 1 | B12: A | C12: North end of 2nd Street | L12: 31.65111
L13: -97.47799
A14: Description Of Damage
A15: Debris collected from Storm Event. Applicant has minimal means of picking up and removing debris, thus cost will be on the higher side. Estimated stack with 100 CY with more to be added.
A19: Impact: | B19: Minor | H19: % Complete | K19: Cost Estimate
H20: 75 | K20: 3080
A21: Site No. | B21: Category | C21: Location (Use map location, address, etc.): | L21: GPS
A24: Description Of Damage
A29: Impact: | H29: % Complete | K29: Cost Estimate
A31: Site No. | B31: Category | C31: Location (Use map location, address, etc.): | L31: GPS
A34: Description Of Damage
A39: Impact: | H39: % Complete | K39: Cost Estimate
A41: Site No. | B41: Category | C41: Location (Use map location, address, etc.): | L41: GPS
A44: Description Of Damage
A49: Impact: | H49: % Complete | K49: Cost Estimate
A51: Name Of Inspector | D51: Agency | G51: Phone No. Office | K51: Phone No.CELL
A52: ='Summary Sheet'!E67 -> Vernon Lansford | D52: ='Summary Sheet'!G67 -> FEMA | G52: =IF('Bosque Co'!G52=0,"",'Bosque Co'!G52) | K52: ='Summary Sheet'!I67 -> 225-910-5272
A54: FEMA Form 90-81, Jan 84 | G54: GRAND TOTAL SHEET 2 | K54: =+K20+K30+K40+K50 -> 3080
A56: 1. Asphalt (3100) $5.30/SY/IN | D56: 8. Grading Roads (3072) $0.10/SY | G56: 15. CMP 48" (3358) $62/LF | K56: 22. Auto Police (8073) $14.35/HR
A57: 2. Aggregate Surface (3011) $13/CY | D57: 9. Rip Rap (3250) $35/CY | G57: 16. CMP 60" (3354) $76/LF | K57: 23. CMD Center (9999) $339/HR
A58: 3. Aggregate Base (3091) $19.50/CY | D58: 10. Bridge Railing 3" (3294) $35/LF | G58: 17. CMP 72" (3354) $115/LF | K58: 24. Helo, Rescue (9999) $6277/HR
A59: 4. Chip & Seal Single (3080) $1.55/SY | D59: 11. Debris C&D (1012) $3.50/CY | G59: 18. CMP 120" (3364) $175/LF | K59: 25. Boat RBS (9999) $323/HR
A60: 5. Chip & Seal Double (3081) $2.79/SY | D60: 12. Debris Veg. (1015) $6/CY | G60: 19. Pickup (8804) $19.90/HR | K60: 26. Boat Utility (9999) $980/HR
A61: 6. Chip & Seal Triple (3082) $4.03/SY | D61: 13. CMP 24" (3354) $30/LF | G61: 20. Trailer, 30 T (8600) $9.90/HR | K61: 27. Person, Vol. (9999) $10/HR
A62: 7. Fill Unclas (3020) $7/CY | D62: 14. CMP 36" (3354) $41/LF | G62: 21. Bus, Large (8182) $30.00/HR | K62: 28. Canine & Handler (9999) $30/HR

Sheet S6
A1: Federal Emergency Management Agency | L1: Date
A2: Preliminary Damage Assessment Site Estimate
A3: Part 1 - Applicant Information
A4: County | C4: Name Of Applicant | G4: Name Of Local Contact | L4: Contact Phone #
A6: Part 2 - Site Information
A7: Key For Damage Category (Use appropriate letters in the "category" blocks below)
B8: a. Debris Removal | E8: d. Water Control Facilities | I8: g. Other Recreation
B9: b. Protective Measures | E9: e. Public Buildings
B10: c. Roads And Bridges | E10: f. Public Utilities
A11: Site No. | B11: Category | C11: Location (Use map location, address, etc.): | L11: GPS | O11: * NEEDS MITIGATION
A14: Description Of Damage
A19: Impact: | H19: % Complete | K19: Cost Estimate
A21: Site No. | B21: Category | C21: Location (Use map location, address, etc.): | L21: GPS
A24: Description Of Damage
A29: Impact: | H29: % Complete | K29: Cost Estimate
A31: Site No. | B31: Category | C31: Location (Use map location, address, etc.): | L31: GPS
A34: Description Of Damage
A39: Impact: | H39: % Complete | K39: Cost Estimate
A41: Site No. | B41: Category | C41: Location (Use map location, address, etc.): | L41: GPS
A44: Description Of Damage
A49: Impact: | H49: % Complete | K49: Cost Estimate
A51: Name Of Inspector | D51: Agency | G51: Phone No. Office | K51: Phone No.CELL
A52: ='Summary Sheet'!E67 -> Vernon Lansford | D52: ='Summary Sheet'!G67 -> FEMA | G52: =IF('Bosque Co'!G52=0,"",'Bosque Co'!G52) | K52: ='Summary Sheet'!I67 -> 225-910-5272
A54: FEMA Form 90-81, Jan 84 | G54: GRAND TOTAL SHEET 2 | K54: =+K20+K30+K40+K50 -> 0
A56: 1. Asphalt (3100) $5.30/SY/IN | D56: 8. Grading Roads (3072) $0.10/SY | G56: 15. CMP 48" (3358) $62/LF | K56: 22. Auto Police (8073) $14.35/HR
A57: 2. Aggregate Surface (3011) $13/CY | D57: 9. Rip Rap (3250) $35/CY | G57: 16. CMP 60" (3354) $76/LF | K57: 23. CMD Center (9999) $339/HR
A58: 3. Aggregate Base (3091) $19.50/CY | D58: 10. Bridge Railing 3" (3294) $35/LF | G58: 17. CMP 72" (3354) $115/LF | K58: 24. Helo, Rescue (9999) $6277/HR
A59: 4. Chip & Seal Single (3080) $1.55/SY | D59: 11. Debris C&D (1012) $3.50/CY | G59: 18. CMP 120" (3364) $175/LF | K59: 25. Boat RBS (9999) $323/HR
A60: 5. Chip & Seal Double (3081) $2.79/SY | D60: 12. Debris Veg. (1015) $6/CY | G60: 19. Pickup (8804) $19.90/HR | K60: 26. Boat Utility (9999) $980/HR
A61: 6. Chip & Seal Triple (3082) $4.03/SY | D61: 13. CMP 24" (3354) $30/LF | G61: 20. Trailer, 30 T (8600) $9.90/HR | K61: 27. Person, Vol. (9999) $10/HR
A62: 7. Fill Unclas (3020) $7/CY | D62: 14. CMP 36" (3354) $41/LF | G62: 21. Bus, Large (8182) $30.00/HR | K62: 28. Canine & Handler (9999) $30/HR

Sheet Time Calc
A1: =TEXT(B1, "dddd") -> Tuesday | B1: 41618.635 | C1: Through | D1: =TEXT(E1, "dddd") -> Tuesday | E1: 41618.75 | F1: =SUM(E1-B1)*24 -> 2.7644444
A2: =TEXT(B2, "dddd") -> Friday | B2: 41621.49 | C2: Through | D2: =TEXT(E2, "dddd") -> Saturday | E2: 41622.083 | F2: =SUM(E2-B2)*24 -> 14.233333
A3: =TEXT(B3, "dddd") -> Tuesday | B3: 41275.5 | C3: Through | D3: =TEXT(E3, "dddd") -> Tuesday | E3: 41275.5 | F3: =SUM(E3-B3)*24 -> 0
A4: =TEXT(B4, "dddd") -> Tuesday | B4: 41275.5 | C4: Through | D4: =TEXT(E4, "dddd") -> Tuesday | E4: 41275.5 | F4: =SUM(E4-B4)*24 -> 0
A5: =TEXT(B5, "dddd") -> Tuesday | B5: 41275.5 | C5: Through | D5: =TEXT(E5, "dddd") -> Tuesday | E5: 41275.5 | F5: =SUM(E5-B5)*24 -> 0
A6: =TEXT(B6, "dddd") -> Tuesday | B6: 41275.5 | C6: Through | D6: =TEXT(E6, "dddd") -> Tuesday | E6: 41275.5 | F6: =SUM(E6-B6)*24 -> 0
A7: =TEXT(B7, "dddd") -> Tuesday | B7: 41275.5 | C7: Through | D7: =TEXT(E7, "dddd") -> Tuesday | E7: 41275.5 | F7: =SUM(E7-B7)*24 -> 0
A8: =TEXT(B8, "dddd") -> Tuesday | B8: 41275.5 | C8: Through | D8: =TEXT(E8, "dddd") -> Tuesday | E8: 41275.5 | F8: =SUM(E8-B8)*24 -> 0
A9: =TEXT(B9, "dddd") -> Tuesday | B9: 41275.5 | C9: Through | D9: =TEXT(E9, "dddd") -> Tuesday | E9: 41275.5 | F9: =SUM(E9-B9)*24 -> 0
A10: =TEXT(B10, "dddd") -> Tuesday | B10: 41275.5 | C10: Through | D10: =TEXT(E10, "dddd") -> Tuesday | E10: 41275.5 | F10: =SUM(E10-B10)*24 -> 0
A11: =TEXT(B11, "dddd") -> Tuesday | B11: 41275.5 | C11: Through | D11: =TEXT(E11, "dddd") -> Tuesday | E11: 41275.5 | F11: =SUM(E11-B11)*24 -> 0
A12: =TEXT(B12, "dddd") -> Tuesday | B12: 41275.5 | C12: Through | D12: =TEXT(E12, "dddd") -> Tuesday | E12: 41275.5 | F12: =SUM(E12-B12)*24 -> 0
... A46: =TEXT(B46, "dddd") -> Thursday | B46: 41298.5 | C46: Through | D46: =TEXT(E46, "dddd") -> Thursday | E46: 41298.5 | F46: =SUM(E46-B46)*24 -> 0
F48: =SUM(F1:F46) -> 16.997778

Sheet FEMAcostcodes
A1: femacode | B1: Insert the date the cost codes were updated: | F1: 40436
A2: Cost Code | B2: Cost Code Description | C2: Unit | D2: Unit Price | E2: Detailed Description | F2: HP | G2: Capacity | H2: Date Updated
A3: cost_cd | B3: cd_desc | C3: uom | D3: unit_price | E3: dtl_desc
A4: 0000 | B4: WORK COMPLETED | C4: LS | D4: $ 0.00 | H4: 39462 | I4: =IF(B4="","",B4) -> WORK COMPLETED
A5: 0000 | B5: WORK TO BE COMPLETED | C5: LS | D5: $ 0.00 | H5: 39462 | I5: =IF(B5="","",B5) -> WORK TO BE COMPLETED
A6: 0909 | B6: MITIGATION | C6: LS | D6: $ 0.00 | E6: 406 MITIGATION | H6: 39462 | I6: =IF(B6="","",B6) -> MITIGATION
A7: 9000 | B7: CEF COST ESTIMATE | C7: LS | D7: $ 0.00 | E7: CEF COST ESTIMATE | H7: 39462 | I7: =IF(B7="","",B7) -> CEF COST ESTIMATE
A8: 9001 | B8: CONTRACT | C8: LS | D8: $ 0.00 | E8: CONTRACT | H8: 39462 | I8: =IF(B8="","",B8) -> CONTRACT
A9: 9003 | B9: CONTRACT COSTS | C9: LS | D9: $ 0.00 | E9: CONTRACT COSTS | H9: 39462 | I9: =IF(B9="","",B9) -> CONTRACT COSTS
A10: 9004 | B10: RENTED EQUIPMENT | C10: LS | D10: $ 0.00 | E10: RENTED EQUIPMENT | H10: 39462 | I10: =IF(B10="","",B10) -> RENTED EQUIPMENT
A11: 9005 | B11: LABOR, O/T W/O BENEFITS | C11: LS | D11: $ 0.00 | E11: LABOR, O/T W/O BENEFITS | H11: 39462 | I11: =IF(B11="","",B11) -> LABOR, O/T W/O BENEFITS
A12: 9006 | B12: LABOR, W/O BENEFITS | C12: LS | D12: $ 0.00 | E12: LABOR, W/O BENEFITS | H12: 39462 | I12: =IF(B12="","",B12) -> LABOR, W/O BENEFITS
A13: 9007 | B13: LABOR | C13: LS | D13: $ 0.00 | E13: LABOR | H13: 39462 | I13: =IF(B13="","",B13) -> LABOR
A14: 9008 | B14: EQUIPMENT | C14: LS | D14: $ 0.00 | E14: EQUIPMENT | H14: 39462 | I14: =IF(B14="","",B14) -> EQUIPMENT
A15: 9009 | B15: MATERIAL | C15: LS | D15: $ 0.00 | E15: MATERIAL | H15: 39462 | I15: =IF(B15="","",B15) -> MATERIAL
A16: 9010 | B16: LABORER REGULAR TIME | C16: HR | D16: $ 0.00 | E16: LABORER REGULAR TIME | H16: 39462 | I16: =IF(B16="","",B16) -> LABORER REGULAR TIME
A17: 9011 | B17: LABORER OVERTIME | C17: HR | D17: $ 0.00 | E17: LABORER OVERTIME | H17: 39462 | I17: =IF(B17="","",B17) -> LABORER OVERTIME
A18: 9012 | B18: EQUIPMENT OPERATOR REGULAR TIME | C18: HR | D18: $ 0.00 | E18: EQUIPMENT OPERATOR REGULAR TIME | H18: 39462 | I18: =IF(B18="","",B18) -> EQUIPMENT OPERATOR REGULAR TIME
... A35: 5905 | B35: DEDUCT ANTICIPATED FLOOD INSURANCE PROCEEDS - LS | C35: LS | D35: $ 0.00 | E35: DEDUCT ANTICIPATED FLOOD INSURANCE PROCEEDS | H35: 39462 | I35: =IF(B35="","",B35) -> DEDUCT ANTICIPATED FLOOD INSURANCE PROCEEDS - LS
I36: =IF(B36="","",B36)
A37: 0000 | B37: Work Completed | C37: LS | D37: 0 | H37: 39645 | I37: =IF(B37="","",B37) -> Work Completed
A38: 0000 | B38: Work to be Completed | C38: LS | D38: 0 | H38: 39645 | I38: =IF(B38="","",B38) -> Work to be Completed
A39: 0909 | B39: MITIGATION | C39: LS | D39: 0 | H39: 39645 | I39: =IF(B39="","",B39) -> MITIGATION
A40: 1001 | B40: DEBRIS (SEDIMENTS, CONCENTRATED) | C40: TON | D40: 0 | H40: 39645 | I40: =IF(B40="","",B40) -> DEBRIS (SEDIMENTS, CONCENTRATED)
A41: 1002 | B41: DEBRIS (SEDIMENTS, SCATTERED) | C41: TON | D41: 0 | H41: 39645 | I41: =IF(B41="","",B41) -> DEBRIS (SEDIMENTS, SCATTERED)
A42: 1003 | B42: DEBRIS (Personal Property Curb) | C42: TON | D42: 0 | H42: 39645 | I42: =IF(B42="","",B42) -> DEBRIS (Personal Property Curb)
A43: 1004 | B43: DEBRIS (TREES & LIMBS, CONCENTRATED) | C43: TON | D43: 0 | H43: 39645 | I43: =IF(B43="","",B43) -> DEBRIS (TREES & LIMBS, CONCENTRATED)
A44: 1005 | B44: DEBRIS (TREES & LIMBS, SCATTERED) | C44: TON | D44: 0 | H44: 39644 | I44: =IF(B44="","",B44) -> DEBRIS (TREES & LIMBS, SCATTERED)
A45: 1010 | B45: DEBRIS (SEDIMENTS, CONCENTRATED) | C45: CY | D45: 3.3 | H45: 39869 | I45: =IF(B45="","",B45) -> DEBRIS (SEDIMENTS, CONCENTRATED)
A46: 1011 | B46: DEBRIS (SEDIMENTS, SCATTERED) | C46: CY | D46: 4 | H46: 39869 | I46: =IF(B46="","",B46) -> DEBRIS (SEDIMENTS, SCATTERED)
A47: 1012 | B47: DEBRIS (Personal Property Curb) | C47: CY | D47: 3.5 | H47: 39552 | I47: =IF(B47="","",B47) -> DEBRIS (Personal Property Curb)
A48: 1014 | B48: DEBRIS (TREES & LIMBS, CONCENTRATED) | C48: CY | D48: 4 | H48: 39552 | I48: =IF(B48="","",B48) -> DEBRIS (TREES & LIMBS, CONCENTRATED)
... A60: 1041 | B60: DEBRIS STUMPS REMOVAL (UPROOTED 19" - 36" DIAMETER) | C60: CY | D60: 32 | H60: 40878 | I60: =IF(B60="","",B60) -> DEBRIS STUMPS REMOVAL (UPROOTED 19" - 36" DIAMETER)
A61: 1042 | B61: DEBRIS STUMPS REMOVAL (UPROOTED 37" DIAMETER AND OVER) | C61: CY | D61: 36 | H61: NIN | I61: =IF(B61="","",B61) -> DEBRIS STUMPS REMOVAL (UPROOTED 37" DIAMETER AND OVER)
A62: 1043 | B62: DEBRIS STUMPS REMOVAL (UPROOTED 24"-36" DIAMETER) | C62: EA | D62: 200 | H62: 39869 | I62: =IF(B62="","",B62) -> DEBRIS STUMPS REMOVAL (UPROOTED 24"-36" DIAMETER)
A63: 1044 | B63: DEBRIS STUMPS REMOVAL (UPROOTED 37" DIAMETER AND OVER) | C63: EA | D63: 250 | H63: 39869 | I63: =IF(B63="","",B63) -> DEBRIS STUMPS REMOVAL (UPROOTED 37" DIAMETER AND OVER)
A64: 1050 | B64: DUMP CHARGES (BURN - BURY) | C64: CY | D64: 1 | H64: 39552 | I64: =IF(B64="","",B64) -> DUMP CHARGES (BURN - BURY)
A65: 1051 | B65: DUMP CHARGES (LANDFILL DISPOSAL) | C65: CY | D65: 1.75 | H65: 39552 | I65: =IF(B65="","",B65) -> DUMP CHARGES (LANDFILL DISPOSAL)
A66: 1052 | B66: DUMP CHARGES (LANDFILL DISPOSAL) | C66: TON | D66: 4 | H66: 39624 | I66: =IF(B66="","",B66) -> DUMP CHARGES (LANDFILL DISPOSAL)
A67: 1060 | B67: DEBRIS CONTAINERS (W/0 DUMP CHARGES) 2 CY PER PICKUP | C67: EA | D67: 5 | H67: 39552 | I67: =IF(B67="","",B67) -> DEBRIS CONTAINERS (W/0 DUMP CHARGES) 2 CY PER PICKUP
A68: 1061 | B68: DEBRIS CONTAINERS (W/0 DUMP CHARGES) 3 CY PER PICKUP | C68: EA | D68: 7.5 | H68: 39552 | I68: =IF(B68="","",B68) -> DEBRIS CONTAINERS (W/0 DUMP CHARGES) 3 CY PER PICKUP
A69: 1062 | B69: DEBRIS CONTAINERS (W/0 DUMP CHARGES) 4 CY PER PICKUP | C69: EA | D69: 10 | H69: 39552 | I69: =IF(B69="","",B69) -> DEBRIS CONTAINERS (W/0 DUMP CHARGES) 4 CY PER PICKUP
A70: 1063 | B70: DEBRIS CONTAINERS (W/O DUMP CHARGES) 8 CY PER PICKUP | C70: EA | D70: 20 | H70: 39552 | I70: =IF(B70="","",B70) -> DEBRIS CONTAINERS (W/O DUMP CHARGES) 8 CY PER PICKUP
A71: 1064 | B71: DEBRIS CONTAINERS (W/O DUMP CHARGES) 20 CY PER PICKUP | C71: EA | D71: 155 | H71: 39552 | I71: =IF(B71="","",B71) -> DEBRIS CONTAINERS (W/O DUMP CHARGES) 20 CY PER PICKUP
A72: 1065 | B72: DEBRIS CONTAINERS (W/O DUMP CHARGES) 30 CY PER PICKUP | C72: EA | D72: 165 | H72: 39552 | I72: =IF(B72="","",B72) -> DEBRIS CONTAINERS (W/O DUMP CHARGES) 30 CY PER PICKUP
A73: 1066 | B73: DEBRIS CONTAINERS (W/O DUMP CHARGES) 40 CY PER PICKUP | C73: EA | D73: 175 | H73: 39552 | I73: =IF(B73="","",B73) -> DEBRIS CONTAINERS (W/O DUMP CHARGES) 40 CY PER PICKUP
... A114: 3015 | B114: SHELL SURFACE (7.75/TON) | C114: TON | D114: 16.5 | H114: 39553 | I114: =IF(B114="","",B114) -> SHELL SURFACE (7.75/TON)
A115: 3016 | B115: AGGREGATE SURFACE (SAME AS 3012 EXCEPT IN CY) | C115: CY | D115: 15 | H115: 39462 | I115: =IF(B115="","",B115) -> AGGREGATE SURFACE (SAME AS 3012 EXCEPT IN CY)
A116: 3020 | B116: FILL (UNCLASSIFIED) | C116: CY | D116: 7 | H116: 40878 | I116: =IF(B116="","",B116) -> FILL (UNCLASSIFIED)
A117: 3021 | B117: HAUL, ADDITIONAL YARD MILE, PURCHASED-DELIVERED | C117: EA | D117: 0.18 | H117: 40878 | I117: =IF(B117="","",B117) -> HAUL, ADDITIONAL YARD MILE, PURCHASED-DELIVERED
A118: 3022 | B118: HAUL, ADDITIONAL TON MILE, PURCHASED-DELIVERED | C118: EA | D118: 0.13 | H118: 40878 | I118: =IF(B118="","",B118) -> HAUL, ADDITIONAL TON MILE, PURCHASED-DELIVERED
A119: 3023 | B119: LIME STABILIZATION (6 INCH DEPTH) | C119: SY | D119: 1.75 | H119: 40878 | I119: =IF(B119="","",B119) -> LIME STABILIZATION (6 INCH DEPTH)
A120: 3030 | B120: LOCAL BORROW (MATERIAL ONLY) | C120: CY | D120: 1.8 | H120: 39553 | I120: =IF(B120="","",B120) -> LOCAL BORROW (MATERIAL ONLY)
A121: 3040 | B121: BACKFILL (GRANULAR) | C121: CY | D121: 12 | H121: 39553 | I121: =IF(B121="","",B121) -> BACKFILL (GRANULAR)
A122: 3050 | B122: EXCAVATION & BACKFILL (SMALL UNCLASSIFIED) | C122: CY | D122: 7.5 | H122: 39553 | I122: =IF(B122="","",B122) -> EXCAVATION & BACKFILL (SMALL UNCLASSIFIED)
A123: 3051 | B123: ROCKFILL (ALT TO UNCLASSIFIED FILL) | C123: CY | D123: 6 | H123: 40878 | I123: =IF(B123="","",B123) -> ROCKFILL (ALT TO UNCLASSIFIED FILL)
A124: 3060 | B124: GRADING (SUBGRADE SHAPING) | C124: SY | D124: 0.6 | H124: 39553 | I124: =IF(B124="","",B124) -> GRADING (SUBGRADE SHAPING)
A125: 3061 | B125: SCARIFYING | C125: SY | D125: 0.7 | H125: 39553 | I125: =IF(B125="","",B125) -> SCARIFYING
A126: 3062 | B126: SCARIFY, RESHAPE AND COMPACT | C126: SY | D126: 2.5 | H126: 39462 | I126: =IF(B126="","",B126) -> SCARIFY, RESHAPE AND COMPACT
A127: 3070 | B127: DITCH CLEANING & SHAPING | C127: LF | D127: 3.4 | H127: 39553 | I127: =IF(B127="","",B127) -> DITCH CLEANING & SHAPING
... A241: 4021 | B241: EXCAVATION (ONLY) | C241: CY | D241: 4.5 | H241: 39462 | I241: =IF(B241="","",B241) -> EXCAVATION (ONLY)
A242: 4030 | B242: FILL (COMPACTED CLAY) | C242: CY | D242: $ 14.00 | H242: 39554 | I242: =IF(B242="","",B242) -> FILL (COMPACTED CLAY)
A243: 4040 | B243: FILL (GRANULAR) | C243: CY | D243: 12 | H243: 39554 | I243: =IF(B243="","",B243) -> FILL (GRANULAR)
A244: 4050 | B244: CONCRETE REMOVAL, REINFORCED | C244: CY | D244: 45 | H244: 39554 | I244: =IF(B244="","",B244) -> CONCRETE REMOVAL, REINFORCED
A245: 4060 | B245: CONCRETE (CLASS X) REINFORCED | C245: CY | D245: 350 | H245: 39554 | I245: =IF(B245="","",B245) -> CONCRETE (CLASS X) REINFORCED
A246: 4070 | B246: RIP RAP (DUMPED) | C246: CY | D246: 17 | H246: 40878 | I246: =IF(B246="","",B246) -> RIP RAP (DUMPED)
A247: 4080 | B247: RIP RAP (GROUTED) | C247: CY | D247: 53 | H247: 40878 | I247: =IF(B247="","",B247) -> RIP RAP (GROUTED)
A248: 4081 | B248: SLOPE PROTECTION (PLACED) | C248: CY | D248: 30 | H248: 39554 | I248: =IF(B248="","",B248) -> SLOPE PROTECTION (PLACED)
A249: 4090 | B249: CONCRETE CHANNEL LINING (REINFORCED) | C249: CY | D249: 150 | H249: 39554 | I249: =IF(B249="","",B249) -> CONCRETE CHANNEL LINING (REINFORCED)
A250: 4100 | B250: ROCK & WIRE BASKETS (GABIONS) | C250: CY | D250: 120 | H250: 39554 | I250: =IF(B250="","",B250) -> ROCK & WIRE BASKETS (GABIONS)
A251: 4101 | B251: GABION BASKET REMOVAL | C251: CY | D251: 3 | H251: 39554 | I251: =IF(B251="","",B251) -> GABION BASKET REMOVAL
A252: 4110 | B252: FILTER BLANKET (PEA GRAVEL) | C252: CY | D252: 12 | H252: 39554 | I252: =IF(B252="","",B252) -> FILTER BLANKET (PEA GRAVEL)
A253: 4120 | B253: RIP RAP REPAIR OF FABRIC FILTER | C253: CY | D253: 35 | H253: 39554 | I253: =IF(B253="","",B253) -> RIP RAP REPAIR OF FABRIC FILTER
A254: 4130 | B254: RIP RAP FABRIC FOR UNDER | C254: SY | D254: 1.5 | H254: 39554 | I254: =IF(B254="","",B254) -> RIP RAP FABRIC FOR UNDER
A255: 4140 | B255: AGGREGATE SURFACE MATERIAL | C255: TON | D255: 6.5 | H255: 39554 | I255: =IF(B255="","",B255) -> AGGREGATE SURFACE MATERIAL
A256: 4141 | B256: AGGREGATE SURFACE MATERIAL | C256: CY | D256: 13 | H256: 39554 | I256: =IF(B256="","",B256) -> AGGREGATE SURFACE MATERIAL
A257: 4150 | B257: AUGERING (DRAIN TILE) | C257: LF | D257: 0.65 | H257: 39554 | I257: =IF(B257="","",B257) -> AUGERING (DRAIN TILE)
A258: 5010 | B258: DEBRIS - INTERIOR REMOVAL AND WALL & FLOOR CLEANING | C258: SF | D258: 0.4 | H258: 39554 | I258: =IF(B258="","",B258) -> DEBRIS - INTERIOR REMOVAL AND WALL & FLOOR CLEANING
A259: 5020 | B259: FLOOR TILE REMOVAL | C259: SF | D259: 0.5 | H259: 39554 | I259: =IF(B259="","",B259) -> FLOOR TILE REMOVAL
A260: 5030 | B260: CARPET REMOVAL | C260: SY | D260: 1 | H260: 39554 | I260: =IF(B260="","",B260) -> CARPET REMOVAL
A261: 5031 | B261: CEILING, SUSPENSION SYSTEM (W/O TILE) | C261: SF | D261: 1.24 | H261: 40878 | I261: =IF(B261="","",B261) -> CEILING, SUSPENSION SYSTEM (W/O TILE)
A262: 5032 | B262: CELIING TILE, 12 X 12" GLUE | C262: SF | D262: 1.63 | H262: 40878 | I262: =IF(B262="","",B262) -> CELIING TILE, 12 X 12" GLUE
A263: 5033 | B263: CEILING TILE 12 X12" TACKED | C263: EA | D263: 1.63 | H263: 40878 | I263: =IF(B263="","",B263) -> CEILING TILE 12 X12" TACKED
A264: 5034 | B264: CEILING TILE, ACCOUSTICAL, 2 X 4' | C264: SF | D264: 1.24 | H264: 40878 | I264: =IF(B264="","",B264) -> CEILING TILE, ACCOUSTICAL, 2 X 4'
A265: 5035 | B265: CELING TILE, W/SUSPENDED METAL SYSTEM | C265: SF | D265: 2.48 | H265: 40878 | I265: =IF(B265="","",B265) -> CELING TILE, W/SUSPENDED METAL SYSTEM
A266: 5040 | B266: MASONRY WALL (8") REMOVAL | C266: SF | D266: 2.17 | H266: 40878 | I266: =IF(B266="","",B266) -> MASONRY WALL (8") REMOVAL
A267: 5050 | B267: FLOOR VINYL BASE REMOVE AND REPLACE | C267: LF | D267: 1.5 | H267: 40878 | I267: =IF(B267="","",B267) -> FLOOR VINYL BASE REMOVE AND REPLACE
... A294: 5097 | B294: SIDING, ALUMINUM (HORIZONTAL) 7" | C294: SF | D294: 2.55 | H294: 40878 | I294: =IF(B294="","",B294) -> SIDING, ALUMINUM (HORIZONTAL) 7"
A295: 5098 | B295: SIDING, BOARD & BATTEN | C295: SF | D295: 3.14 | H295: NIN | I295: =IF(B295="","",B295) -> SIDING, BOARD & BATTEN
A296: 5099 | B296: SIDING, FACIA BOARD | C296: LF | D296: 1.95 | H296: 40878 | I296: =IF(B296="","",B296) -> SIDING, FACIA BOARD
A297: 5100 | B297: MASONRY SURFACE BRICK SANDBLAST CLEANING | C297: SF | D297: 1.59 | H297: 40878 | I297: =IF(B297="","",B297) -> MASONRY SURFACE BRICK SANDBLAST CLEANING
A298: 5101 | B298: SIDING, SHIP LAP | C298: SF | D298: 1.65 | H298: NIN | I298: =IF(B298="","",B298) -> SIDING, SHIP LAP
A299: 5102 | B299: SIDING, SOFFIT WOOD | C299: SF | D299: 1.85 | H299: NIN | I299: =IF(B299="","",B299) -> SIDING, SOFFIT WOOD
A300: 5103 | B300: SIDING, VINYL | C300: SF | D300: 1.7 | H300: NIN | I300: =IF(B300="","",B300) -> SIDING, VINYL
A301: 5110 | B301: MASONRY SURFACE BRICK STEAM CLEANING | C301: SF | D301: 0.96 | H301: 39554 | I301: =IF(B301="","",B301) -> MASONRY SURFACE BRICK STEAM CLEANING
A302: 5120 | B302: CARPET CLEANING | C302: SY | D302: 0.5 | H302: 39554 | I302: =IF(B302="","",B302) -> CARPET CLEANING
A303: 5130 | B303: FURNITURE/METAL - CLEAN DISINFECT & REPAIR | C303: EA | D303: 75 | H303: 39554 | I303: =IF(B303="","",B303) -> FURNITURE/METAL - CLEAN DISINFECT & REPAIR
A304: 5140 | B304: MOTOR REPAIR ELECTRIC (1/2 HP), ALLOWANCE | C304: EA | D304: 75 | H304: 40878 | I304: =IF(B304="","",B304) -> MOTOR REPAIR ELECTRIC (1/2 HP), ALLOWANCE
A305: 5141 | B305: MOTOR REPAIR ELECTRIC (7 1/2 HP), ALLOWANCE | C305: EA | D305: 290 | H305: 39554 | I305: =IF(B305="","",B305) -> MOTOR REPAIR ELECTRIC (7 1/2 HP), ALLOWANCE
A306: 5142 | B306: MOTOR REPAIR ELECTRIC (16 HP), ALLOWANCE | C306: EA | D306: 625 | H306: 39554 | I306: =IF(B306="","",B306) -> MOTOR REPAIR ELECTRIC (16 HP), ALLOWANCE
...
